{
  "txcAuth": "kate.hunter@ngtraining1.onmicrosoft.com",
  "randomIdentifier": 5782,
  "tenantId": "957a313a-971b-4add-b513-038b581bc3e7",
  "solutionName": "WarehouseManagement",
  "publisherName": "ALMLab",
  "publisherPrefix": "almlab",
  "repo": "toreveiseth/alm-lab",
  "mainRulesetId": 18265962,
  "mainRulesetName": "alm-lab-main-protection",
  "devEnvName": "Warehouse dev 5782",
  "devEnvDomain": "wm-dev-5782",
  "devEnvUrl": "https://wm-dev-5782.crm4.dynamics.com",
  "devProfile": "dev",
  "testEnvName": "Warehouse test 5782",
  "testEnvDomain": "wm-test-5782",
  "testEnvUrl": "https://wm-test-5782.crm4.dynamics.com",
  "testProfile": "test",
  "appName": "wm-deploy-5782",
  "appId": "909dfc76-b332-4cb6-860a-cca40c7d31c7",
  "appObjectId": "907c1506-1d72-4a1b-9161-174b2264652f",
  "servicePrincipalObjectId": "1e9906e9-dd88-4683-a7d4-daadabe27fca",
  "federatedCredentialName": "github-main",
  "dataverseTestUrl": "https://wm-test-5782.crm4.dynamics.com"
}
